aaiotrello/__init__.py
aaiotrello/actions.py
aaiotrello/boards.py
aaiotrello/cards.py
aaiotrello/checklists.py
aaiotrello/lists.py
aaiotrello/members.py
aaiotrello/notifications.py
aaiotrello/organizations.py
aaiotrello/tokens.py
aaiotrello/types.py
aaiotrello/utils.py
aaiotrello/webhooks.py
aaiotrello-2.0.0.dist-info/LICENSE
aaiotrello-2.0.0.dist-info/METADATA
aaiotrello-2.0.0.dist-info/WHEEL
aaiotrello-2.0.0.dist-info/top_level.txt
aaiotrello-2.0.0.dist-info/RECORD
