Metadata-Version: 2.1
Name: aaiotrello
Version: 2.0.0
Summary: Async Python library for interacting with the Trello API
Home-page: https://trello.com/
Download-URL: https://github.com/developerreva/aaiotrello
Author: Developereva
Author-email: developereva@protonmail.com
License: BSD License
Project-URL: Source Code, https://github.com/developerreva/aaiotrello
Project-URL: Documentation, https://github.com/developerreva/aaiotrello#-getting-started
Project-URL: Trello REST API Documentation, https://developer.atlassian.com/cloud/trello/rest/
Keywords: python python3 api-client aiohttp api-wrapper trello trello-api trello-async
Classifier: Programming Language :: Python :: 3.7
Classifier: License :: OSI Approved :: MIT License
Classifier: Operating System :: OS Independent
Requires: a
Requires: i
Requires: o
Requires: h
Requires: t
Requires: t
Requires: p
License-File: LICENSE
Requires-Dist: aiohttp >=3.9.0
